.installed.cfg
.mr.developer.cfg
.travis.yml
MANIFEST.in
Makefile
README.rst
bootstrap.py
buildout.cfg
setup.py
buildout.d/base.cfg
buildout.d/development.cfg
buildout.d/travis.cfg
buildout.d/versions.cfg
docs/CHANGELOG.rst
docs/LICENSE.rst
src/niteoweb/__init__.py
src/niteoweb/__init__.pyc
src/niteoweb.aweber.egg-info/PKG-INFO
src/niteoweb.aweber.egg-info/SOURCES.txt
src/niteoweb.aweber.egg-info/dependency_links.txt
src/niteoweb.aweber.egg-info/entry_points.txt
src/niteoweb.aweber.egg-info/namespace_packages.txt
src/niteoweb.aweber.egg-info/not-zip-safe
src/niteoweb.aweber.egg-info/requires.txt
src/niteoweb.aweber.egg-info/top_level.txt
src/niteoweb/aweber/__init__.py
src/niteoweb/aweber/__init__.pyc
src/niteoweb/aweber/aweberapi.py
src/niteoweb/aweber/aweberapi.pyc
src/niteoweb/aweber/configure.zcml
src/niteoweb/aweber/controlpanel.py
src/niteoweb/aweber/controlpanel.pyc
src/niteoweb/aweber/interfaces.py
src/niteoweb/aweber/interfaces.pyc
src/niteoweb/aweber/testing.py
src/niteoweb/aweber/testing.pyc
src/niteoweb/aweber/Extensions/__init__.py
src/niteoweb/aweber/Extensions/__init__.pyc
src/niteoweb/aweber/Extensions/install.py
src/niteoweb/aweber/Extensions/install.pyc
src/niteoweb/aweber/profiles/default/controlpanel.xml
src/niteoweb/aweber/profiles/default/metadata.xml
src/niteoweb/aweber/profiles/default/registry.xml
src/niteoweb/aweber/profiles/uninstall/controlpanel.xml
src/niteoweb/aweber/profiles/uninstall/metadata.xml
src/niteoweb/aweber/profiles/uninstall/registry.xml
src/niteoweb/aweber/tests/__init__.py
src/niteoweb/aweber/tests/__init__.pyc
src/niteoweb/aweber/tests/test_aweber.py
src/niteoweb/aweber/tests/test_aweber.pyc
src/niteoweb/aweber/tests/test_setup.py
src/niteoweb/aweber/tests/test_setup.pyc