Metadata-Version: 1.1
Name: niteoweb.aweber
Version: 0.1
Summary: Aweber API integration for Plone.
Home-page: http://pypi.python.org/pypi/niteoweb.aweber
Author: NiteoWeb Ltd.
Author-email: info@niteoweb.com
License: BSD
Keywords: Plone Python aweber
Platform: UNKNOWN
Classifier: Framework :: Plone
Classifier: Programming Language :: Python
